src/__init__.py
src/main.py
src/info/__init__.py
src/info/history.py
src/info/module.py
src/info/required_modules.py
pakage_version_seeker-1.0.4.dist-info/LICENSE
pakage_version_seeker-1.0.4.dist-info/METADATA
pakage_version_seeker-1.0.4.dist-info/WHEEL
pakage_version_seeker-1.0.4.dist-info/entry_points.txt
pakage_version_seeker-1.0.4.dist-info/top_level.txt
pakage_version_seeker-1.0.4.dist-info/RECORD
