Metadata-Version: 2.1
Name: pakage-version-seeker
Version: 1.0.4
Summary: Find unspecified pakages verison!!
Home-page: https://github.com/uinone/package-version-seeker
Author: uinone
Author-email: tizm423@gmail.com
License: MIT
Platform: UNKNOWN
Classifier: Programming Language :: Python :: 3.8
Classifier: Programming Language :: Python :: 3.9
Requires-Python: >=3.8
License-File: LICENSE
Requires-Dist: requests==2.32.3
Requires-Dist: beautifulsoup4==4.12.3
